add.v
module add(sum,carry_overflow,A,B,cin);
	input signed [63:0] A,B;
	input cin;
	output signed [63:0] sum;
	output signed carry_overflow;
	wire [18:0] carry;
	wire [2:0] t1,t2,t3;
	genvar i;
	CLA_FULL c1(sum[3:0],carry[0],A[3:0],B[3:0],cin);
	generate for(i=0;i<14;i=i+1)
		CLA_FULL c2(sum[7+4*i:4+4*i],carry[1+i],A[7+4*i:4+4*i],B[7+4*i:4+4*i],carry[0+i]);
	endgenerate
	CLA_FULL c16(sum[63:60],carry[18],A[63:60],B[63:60],carry[14]);
	generate for(i=0;i<3;i=i+1)
	begin
    		and gate2(t1[i],A[i+60],B[i+60]);
    		and gate3(t2[i],B[i+60],carry[i+14]);
    		and gate4(t3[i],A[i+60],carry[i+14]);
    		or gate5(carry[i+1+14],t1[i],t2[i],t3[i]);
	end
	endgenerate
       	xor(carry_overflow,carry[17],carry[18]);
endmodule 

module PG(p, g, a, b);
	input a, b;
	output p, g;
	and G1 (g, a, b);
	xor G2 (p, a, b);
endmodule

module CLA(g0, p0, g1, p1, g2, p2, g3, p3, c0, c1, c2, c3, c4);
	input g0, p0, g1, p1, g2, p2, g3, p3, c0;
	output c1, c2, c3, c4;
	wire t1, t2, t3, t4, t5, t6, t7, t8, t9, t10;
	and G1(t1, p0, c0);
	or G2(c1, t1, g0);
	
	and G3(t2, c0, p0, p1);
	and G4(t3, g0, p1);
	or G5(c2, g1, t2, t3);

	and G6(t4, c0, p0, p1, p2);
	and G7(t5, g0, p1, p2);
	and G8(t6, g1, p2);
	or G9(c3, g2, t4, t5, t6);
	
	and G10(t7, c0, p0, p1, p2, p3);
	and G11(t8, g0, p1, p2, p3);
	and G12(t9, g1, p2, p3);
	and G13(t10, g2, p3);
	or G14(c4, g3, t7, t8, t9, t10);
endmodule

module SUM(p0, c0, p1, c1, p2, c2, p3, c3, sum0, sum1, sum2, sum3);
	input p0, c0, p1, c1, p2, c2, p3, c3;
	output sum0, sum1, sum2, sum3;
	xor G1(sum0, p0, c0);
	xor G2(sum1, p1, c1);
	xor G3(sum2, p2, c2);
	xor G4(sum3, p3, c3);
endmodule

module CLA_FINAL(a3, b3, a2, b2, a1, b1, a0, b0, c0, c4, sum3, sum2, sum1, sum0);
	input a3, b3, a2, b2, a1, b1, a0, b0, c0;
	output c4, sum3, sum2, sum1, sum0;
	wire g0, p0, g1, p1, g2, p2, g3, p3, c1, c2, c3;
	PG B1(p0, g0, a0, b0);
	PG B2(p1, g1, a1, b1);
	PG B3(p2, g2, a2, b2);
	PG B4(p3, g3, a3, b3);
	CLA B5(g0, p0, g1, p1, g2, p2, g3, p3, c0, c1, c2, c3, c4);
	SUM B6(p0, c0, p1, c1, p2, c2, p3, c3, sum0, sum1, sum2, sum3);
endmodule

module CLA_FULL(sum,cout,a,b,cin);
	input [3:0] a,b;
	input cin;
	output [3:0] sum;
	output cout;
	CLA_FINAL F1(a[3], b[3], a[2], b[2], a[1], b[1], a[0], b[0], cin, cout, sum[3], sum[2], sum[1], sum[0]);
endmodule

add_tb.v
`include"add.v"
`timescale 1ps / 1ps 
module testbench;
	reg [63:0] a,b;
	reg cin;
	wire [63:0] out;
	wire c;
	integer i,k;
	add DUT(out,c,a,b,cin);
	initial begin
	//$monitor ($time,"ns: a = %b,\n\t\t        b = %b,\n\t\t       sum= %b, carry=%b \n",a, b, out,c); 
	$dumpfile("add.vcd");
    	$dumpvars(0,a,b,c,out);
	b=2**10-1;
	a=2**10-1;
	cin=0;
	#10;
	for(i=0; i<=2**4-1; i++) begin
		a=2**10-1;
		for(k=0;k<=2**4-1;k++) begin
		a--;
		#10;
		end
		b--;
	end
	end
endmodule

and64.vcd
$date
	Wed Feb 02 20:42:41 2022
$end
$version
	Icarus Verilog
$end
$timescale
	10ns
$end
$scope module testbench $end
$var reg 64 ! a [63:0] $end
$upscope $end
$scope module testbench $end
$var reg 64 " b [63:0] $end
$upscope $end
$scope module testbench $end
$var wire 64 # out [63:0] $end
$upscope $end
$enddefinitions $end
#0
$dumpvars
b11111111111111111111111111111111 #
b11111111111111111111111111111111 "
b11111111111111111111111111111111 !
$end
#1
b11111111111111111111111111111110 #
b11111111111111111111111111111110 !
#2
b11111111111111111111111111111101 #
b11111111111111111111111111111101 !
#3
b11111111111111111111111111111100 #
b11111111111111111111111111111100 !
#4
b11111111111111111111111111111011 #
b11111111111111111111111111111011 !
#5
b11111111111111111111111111111010 #
b11111111111111111111111111111010 !
#6
b11111111111111111111111111111001 #
b11111111111111111111111111111001 !
#7
b11111111111111111111111111111000 #
b11111111111111111111111111111000 !
#8
b11111111111111111111111111110111 #
b11111111111111111111111111110111 !
#9
b11111111111111111111111111110110 #
b11111111111111111111111111110110 !
#10
b11111111111111111111111111110101 #
b11111111111111111111111111110101 !
#11
b11111111111111111111111111110100 #
b11111111111111111111111111110100 !
#12
b11111111111111111111111111110011 #
b11111111111111111111111111110011 !
#13
b11111111111111111111111111110010 #
b11111111111111111111111111110010 !
#14
b11111111111111111111111111110001 #
b11111111111111111111111111110001 !
#15
b11111111111111111111111111110000 #
b11111111111111111111111111110000 !
#16
b11111111111111111111111111101111 #
b11111111111111111111111111101111 !
#17
b11111111111111111111111110011010 #
b11111111111111111111111111111110 !
b11111111111111111111111110011011 "
#18
b11111111111111111111111110011001 #
b11111111111111111111111111111101 !
#19
b11111111111111111111111110011000 #
b11111111111111111111111111111100 !
#20
b11111111111111111111111110011011 #
b11111111111111111111111111111011 !
#21
b11111111111111111111111110011010 #
b11111111111111111111111111111010 !
#22
b11111111111111111111111110011001 #
b11111111111111111111111111111001 !
#23
b11111111111111111111111110011000 #
b11111111111111111111111111111000 !
#24
b11111111111111111111111110010011 #
b11111111111111111111111111110111 !
#25
b11111111111111111111111110010010 #
b11111111111111111111111111110110 !
#26
b11111111111111111111111110010001 #
b11111111111111111111111111110101 !
#27
b11111111111111111111111110010000 #
b11111111111111111111111111110100 !
#28
b11111111111111111111111110010011 #
b11111111111111111111111111110011 !
#29
b11111111111111111111111110010010 #
b11111111111111111111111111110010 !
#30
b11111111111111111111111110010001 #
b11111111111111111111111111110001 !
#31
b11111111111111111111111110010000 #
b11111111111111111111111111110000 !
#32
b11111111111111111111111110001011 #
b11111111111111111111111111101111 !
#33
b11111111111111111111111100110110 #
b11111111111111111111111111111110 !
b11111111111111111111111100110111 "
#34
b11111111111111111111111100110101 #
b11111111111111111111111111111101 !
#35
b11111111111111111111111100110100 #
b11111111111111111111111111111100 !
#36
b11111111111111111111111100110011 #
b11111111111111111111111111111011 !
#37
b11111111111111111111111100110010 #
b11111111111111111111111111111010 !
#38
b11111111111111111111111100110001 #
b11111111111111111111111111111001 !
#39
b11111111111111111111111100110000 #
b11111111111111111111111111111000 !
#40
b11111111111111111111111100110111 #
b11111111111111111111111111110111 !
#41
b11111111111111111111111100110110 #
b11111111111111111111111111110110 !
#42
b11111111111111111111111100110101 #
b11111111111111111111111111110101 !
#43
b11111111111111111111111100110100 #
b11111111111111111111111111110100 !
#44
b11111111111111111111111100110011 #
b11111111111111111111111111110011 !
#45
b11111111111111111111111100110010 #
b11111111111111111111111111110010 !
#46
b11111111111111111111111100110001 #
b11111111111111111111111111110001 !
#47
b11111111111111111111111100110000 #
b11111111111111111111111111110000 !
#48
b11111111111111111111111100100111 #
b11111111111111111111111111101111 !
#49
b11111111111111111111111011010010 #
b11111111111111111111111111111110 !
b11111111111111111111111011010011 "
#50
b11111111111111111111111011010001 #
b11111111111111111111111111111101 !
#51
b11111111111111111111111011010000 #
b11111111111111111111111111111100 !
#52
b11111111111111111111111011010011 #
b11111111111111111111111111111011 !
#53
b11111111111111111111111011010010 #
b11111111111111111111111111111010 !
#54
b11111111111111111111111011010001 #
b11111111111111111111111111111001 !
#55
b11111111111111111111111011010000 #
b11111111111111111111111111111000 !
#56
b11111111111111111111111011010011 #
b11111111111111111111111111110111 !
#57
b11111111111111111111111011010010 #
b11111111111111111111111111110110 !
#58
b11111111111111111111111011010001 #
b11111111111111111111111111110101 !
#59
b11111111111111111111111011010000 #
b11111111111111111111111111110100 !
#60
b11111111111111111111111011010011 #
b11111111111111111111111111110011 !
#61
b11111111111111111111111011010010 #
b11111111111111111111111111110010 !
#62
b11111111111111111111111011010001 #
b11111111111111111111111111110001 !
#63
b11111111111111111111111011010000 #
b11111111111111111111111111110000 !
#64
b11111111111111111111111011000011 #
b11111111111111111111111111101111 !
#65
b11111111111111111111111001101110 #
b11111111111111111111111111111110 !
b11111111111111111111111001101111 "
#66
b11111111111111111111111001101101 #
b11111111111111111111111111111101 !
#67
b11111111111111111111111001101100 #
b11111111111111111111111111111100 !
#68
b11111111111111111111111001101011 #
b11111111111111111111111111111011 !
#69
b11111111111111111111111001101010 #
b11111111111111111111111111111010 !
#70
b11111111111111111111111001101001 #
b11111111111111111111111111111001 !
#71
b11111111111111111111111001101000 #
b11111111111111111111111111111000 !
#72
b11111111111111111111111001100111 #
b11111111111111111111111111110111 !
#73
b11111111111111111111111001100110 #
b11111111111111111111111111110110 !
#74
b11111111111111111111111001100101 #
b11111111111111111111111111110101 !
#75
b11111111111111111111111001100100 #
b11111111111111111111111111110100 !
#76
b11111111111111111111111001100011 #
b11111111111111111111111111110011 !
#77
b11111111111111111111111001100010 #
b11111111111111111111111111110010 !
#78
b11111111111111111111111001100001 #
b11111111111111111111111111110001 !
#79
b11111111111111111111111001100000 #
b11111111111111111111111111110000 !
#80
b11111111111111111111111001101111 #
b11111111111111111111111111101111 !
#81
b11111111111111111111111000001010 #
b11111111111111111111111111111110 !
b11111111111111111111111000001011 "
#82
b11111111111111111111111000001001 #
b11111111111111111111111111111101 !
#83
b11111111111111111111111000001000 #
b11111111111111111111111111111100 !
#84
b11111111111111111111111000001011 #
b11111111111111111111111111111011 !
#85
b11111111111111111111111000001010 #
b11111111111111111111111111111010 !
#86
b11111111111111111111111000001001 #
b11111111111111111111111111111001 !
#87
b11111111111111111111111000001000 #
b11111111111111111111111111111000 !
#88
b11111111111111111111111000000011 #
b11111111111111111111111111110111 !
#89
b11111111111111111111111000000010 #
b11111111111111111111111111110110 !
#90
b11111111111111111111111000000001 #
b11111111111111111111111111110101 !
#91
b11111111111111111111111000000000 #
b11111111111111111111111111110100 !
#92
b11111111111111111111111000000011 #
b11111111111111111111111111110011 !
#93
b11111111111111111111111000000010 #
b11111111111111111111111111110010 !
#94
b11111111111111111111111000000001 #
b11111111111111111111111111110001 !
#95
b11111111111111111111111000000000 #
b11111111111111111111111111110000 !
#96
b11111111111111111111111000001011 #
b11111111111111111111111111101111 !
#97
b11111111111111111111110110100110 #
b11111111111111111111111111111110 !
b11111111111111111111110110100111 "
#98
b11111111111111111111110110100101 #
b11111111111111111111111111111101 !
#99
b11111111111111111111110110100100 #
b11111111111111111111111111111100 !
#100
b11111111111111111111110110100011 #
b11111111111111111111111111111011 !
#101
b11111111111111111111110110100010 #
b11111111111111111111111111111010 !
#102
b11111111111111111111110110100001 #
b11111111111111111111111111111001 !
#103
b11111111111111111111110110100000 #
b11111111111111111111111111111000 !
#104
b11111111111111111111110110100111 #
b11111111111111111111111111110111 !
#105
b11111111111111111111110110100110 #
b11111111111111111111111111110110 !
#106
b11111111111111111111110110100101 #
b11111111111111111111111111110101 !
#107
b11111111111111111111110110100100 #
b11111111111111111111111111110100 !
#108
b11111111111111111111110110100011 #
b11111111111111111111111111110011 !
#109
b11111111111111111111110110100010 #
b11111111111111111111111111110010 !
#110
b11111111111111111111110110100001 #
b11111111111111111111111111110001 !
#111
b11111111111111111111110110100000 #
b11111111111111111111111111110000 !
#112
b11111111111111111111110110100111 #
b11111111111111111111111111101111 !
#113
b11111111111111111111110101000010 #
b11111111111111111111111111111110 !
b11111111111111111111110101000011 "
#114
b11111111111111111111110101000001 #
b11111111111111111111111111111101 !
#115
b11111111111111111111110101000000 #
b11111111111111111111111111111100 !
#116
b11111111111111111111110101000011 #
b11111111111111111111111111111011 !
#117
b11111111111111111111110101000010 #
b11111111111111111111111111111010 !
#118
b11111111111111111111110101000001 #
b11111111111111111111111111111001 !
#119
b11111111111111111111110101000000 #
b11111111111111111111111111111000 !
#120
b11111111111111111111110101000011 #
b11111111111111111111111111110111 !
#121
b11111111111111111111110101000010 #
b11111111111111111111111111110110 !
#122
b11111111111111111111110101000001 #
b11111111111111111111111111110101 !
#123
b11111111111111111111110101000000 #
b11111111111111111111111111110100 !
#124
b11111111111111111111110101000011 #
b11111111111111111111111111110011 !
#125
b11111111111111111111110101000010 #
b11111111111111111111111111110010 !
#126
b11111111111111111111110101000001 #
b11111111111111111111111111110001 !
#127
b11111111111111111111110101000000 #
b11111111111111111111111111110000 !
#128
b11111111111111111111110101000011 #
b11111111111111111111111111101111 !
#129
b11111111111111111111110011011110 #
b11111111111111111111111111111110 !
b11111111111111111111110011011111 "
#130
b11111111111111111111110011011101 #
b11111111111111111111111111111101 !
#131
b11111111111111111111110011011100 #
b11111111111111111111111111111100 !
#132
b11111111111111111111110011011011 #
b11111111111111111111111111111011 !
#133
b11111111111111111111110011011010 #
b11111111111111111111111111111010 !
#134
b11111111111111111111110011011001 #
b11111111111111111111111111111001 !
#135
b11111111111111111111110011011000 #
b11111111111111111111111111111000 !
#136
b11111111111111111111110011010111 #
b11111111111111111111111111110111 !
#137
b11111111111111111111110011010110 #
b11111111111111111111111111110110 !
#138
b11111111111111111111110011010101 #
b11111111111111111111111111110101 !
#139
b11111111111111111111110011010100 #
b11111111111111111111111111110100 !
#140
b11111111111111111111110011010011 #
b11111111111111111111111111110011 !
#141
b11111111111111111111110011010010 #
b11111111111111111111111111110010 !
#142
b11111111111111111111110011010001 #
b11111111111111111111111111110001 !
#143
b11111111111111111111110011010000 #
b11111111111111111111111111110000 !
#144
b11111111111111111111110011001111 #
b11111111111111111111111111101111 !
#145
b11111111111111111111110001111010 #
b11111111111111111111111111111110 !
b11111111111111111111110001111011 "
#146
b11111111111111111111110001111001 #
b11111111111111111111111111111101 !
#147
b11111111111111111111110001111000 #
b11111111111111111111111111111100 !
#148
b11111111111111111111110001111011 #
b11111111111111111111111111111011 !
#149
b11111111111111111111110001111010 #
b11111111111111111111111111111010 !
#150
b11111111111111111111110001111001 #
b11111111111111111111111111111001 !
#151
b11111111111111111111110001111000 #
b11111111111111111111111111111000 !
#152
b11111111111111111111110001110011 #
b11111111111111111111111111110111 !
#153
b11111111111111111111110001110010 #
b11111111111111111111111111110110 !
#154
b11111111111111111111110001110001 #
b11111111111111111111111111110101 !
#155
b11111111111111111111110001110000 #
b11111111111111111111111111110100 !
#156
b11111111111111111111110001110011 #
b11111111111111111111111111110011 !
#157
b11111111111111111111110001110010 #
b11111111111111111111111111110010 !
#158
b11111111111111111111110001110001 #
b11111111111111111111111111110001 !
#159
b11111111111111111111110001110000 #
b11111111111111111111111111110000 !
#160
b11111111111111111111110001101011 #
b11111111111111111111111111101111 !
#161
b11111111111111111111110000010110 #
b11111111111111111111111111111110 !
b11111111111111111111110000010111 "
#162
b11111111111111111111110000010101 #
b11111111111111111111111111111101 !
#163
b11111111111111111111110000010100 #
b11111111111111111111111111111100 !
#164
b11111111111111111111110000010011 #
b11111111111111111111111111111011 !
#165
b11111111111111111111110000010010 #
b11111111111111111111111111111010 !
#166
b11111111111111111111110000010001 #
b11111111111111111111111111111001 !
#167
b11111111111111111111110000010000 #
b11111111111111111111111111111000 !
#168
b11111111111111111111110000010111 #
b11111111111111111111111111110111 !
#169
b11111111111111111111110000010110 #
b11111111111111111111111111110110 !
#170
b11111111111111111111110000010101 #
b11111111111111111111111111110101 !
#171
b11111111111111111111110000010100 #
b11111111111111111111111111110100 !
#172
b11111111111111111111110000010011 #
b11111111111111111111111111110011 !
#173
b11111111111111111111110000010010 #
b11111111111111111111111111110010 !
#174
b11111111111111111111110000010001 #
b11111111111111111111111111110001 !
#175
b11111111111111111111110000010000 #
b11111111111111111111111111110000 !
#176
b11111111111111111111110000000111 #
b11111111111111111111111111101111 !
#177
b11111111111111111111101110110010 #
b11111111111111111111111111111110 !
b11111111111111111111101110110011 "
#178
b11111111111111111111101110110001 #
b11111111111111111111111111111101 !
#179
b11111111111111111111101110110000 #
b11111111111111111111111111111100 !
#180
b11111111111111111111101110110011 #
b11111111111111111111111111111011 !
#181
b11111111111111111111101110110010 #
b11111111111111111111111111111010 !
#182
b11111111111111111111101110110001 #
b11111111111111111111111111111001 !
#183
b11111111111111111111101110110000 #
b11111111111111111111111111111000 !
#184
b11111111111111111111101110110011 #
b11111111111111111111111111110111 !
#185
b11111111111111111111101110110010 #
b11111111111111111111111111110110 !
#186
b11111111111111111111101110110001 #
b11111111111111111111111111110101 !
#187
b11111111111111111111101110110000 #
b11111111111111111111111111110100 !
#188
b11111111111111111111101110110011 #
b11111111111111111111111111110011 !
#189
b11111111111111111111101110110010 #
b11111111111111111111111111110010 !
#190
b11111111111111111111101110110001 #
b11111111111111111111111111110001 !
#191
b11111111111111111111101110110000 #
b11111111111111111111111111110000 !
#192
b11111111111111111111101110100011 #
b11111111111111111111111111101111 !
#193
b11111111111111111111101101001110 #
b11111111111111111111111111111110 !
b11111111111111111111101101001111 "
#194
b11111111111111111111101101001101 #
b11111111111111111111111111111101 !
#195
b11111111111111111111101101001100 #
b11111111111111111111111111111100 !
#196
b11111111111111111111101101001011 #
b11111111111111111111111111111011 !
#197
b11111111111111111111101101001010 #
b11111111111111111111111111111010 !
#198
b11111111111111111111101101001001 #
b11111111111111111111111111111001 !
#199
b11111111111111111111101101001000 #
b11111111111111111111111111111000 !
#200
b11111111111111111111101101000111 #
b11111111111111111111111111110111 !
#201
b11111111111111111111101101000110 #
b11111111111111111111111111110110 !
#202
b11111111111111111111101101000101 #
b11111111111111111111111111110101 !
#203
b11111111111111111111101101000100 #
b11111111111111111111111111110100 !
#204
b11111111111111111111101101000011 #
b11111111111111111111111111110011 !
#205
b11111111111111111111101101000010 #
b11111111111111111111111111110010 !
#206
b11111111111111111111101101000001 #
b11111111111111111111111111110001 !
#207
b11111111111111111111101101000000 #
b11111111111111111111111111110000 !
#208
b11111111111111111111101101001111 #
b11111111111111111111111111101111 !
#209
b11111111111111111111101011101010 #
b11111111111111111111111111111110 !
b11111111111111111111101011101011 "
#210
b11111111111111111111101011101001 #
b11111111111111111111111111111101 !
#211
b11111111111111111111101011101000 #
b11111111111111111111111111111100 !
#212
b11111111111111111111101011101011 #
b11111111111111111111111111111011 !
#213
b11111111111111111111101011101010 #
b11111111111111111111111111111010 !
#214
b11111111111111111111101011101001 #
b11111111111111111111111111111001 !
#215
b11111111111111111111101011101000 #
b11111111111111111111111111111000 !
#216
b11111111111111111111101011100011 #
b11111111111111111111111111110111 !
#217
b11111111111111111111101011100010 #
b11111111111111111111111111110110 !
#218
b11111111111111111111101011100001 #
b11111111111111111111111111110101 !
#219
b11111111111111111111101011100000 #
b11111111111111111111111111110100 !
#220
b11111111111111111111101011100011 #
b11111111111111111111111111110011 !
#221
b11111111111111111111101011100010 #
b11111111111111111111111111110010 !
#222
b11111111111111111111101011100001 #
b11111111111111111111111111110001 !
#223
b11111111111111111111101011100000 #
b11111111111111111111111111110000 !
#224
b11111111111111111111101011101011 #
b11111111111111111111111111101111 !
#225
b11111111111111111111101010000110 #
b11111111111111111111111111111110 !
b11111111111111111111101010000111 "
#226
b11111111111111111111101010000101 #
b11111111111111111111111111111101 !
#227
b11111111111111111111101010000100 #
b11111111111111111111111111111100 !
#228
b11111111111111111111101010000011 #
b11111111111111111111111111111011 !
#229
b11111111111111111111101010000010 #
b11111111111111111111111111111010 !
#230
b11111111111111111111101010000001 #
b11111111111111111111111111111001 !
#231
b11111111111111111111101010000000 #
b11111111111111111111111111111000 !
#232
b11111111111111111111101010000111 #
b11111111111111111111111111110111 !
#233
b11111111111111111111101010000110 #
b11111111111111111111111111110110 !
#234
b11111111111111111111101010000101 #
b11111111111111111111111111110101 !
#235
b11111111111111111111101010000100 #
b11111111111111111111111111110100 !
#236
b11111111111111111111101010000011 #
b11111111111111111111111111110011 !
#237
b11111111111111111111101010000010 #
b11111111111111111111111111110010 !
#238
b11111111111111111111101010000001 #
b11111111111111111111111111110001 !
#239
b11111111111111111111101010000000 #
b11111111111111111111111111110000 !
#240
b11111111111111111111101010000111 #
b11111111111111111111111111101111 !
#241
b11111111111111111111101000100010 #
b11111111111111111111111111111110 !
b11111111111111111111101000100011 "
#242
b11111111111111111111101000100001 #
b11111111111111111111111111111101 !
#243
b11111111111111111111101000100000 #
b11111111111111111111111111111100 !
#244
b11111111111111111111101000100011 #
b11111111111111111111111111111011 !
#245
b11111111111111111111101000100010 #
b11111111111111111111111111111010 !
#246
b11111111111111111111101000100001 #
b11111111111111111111111111111001 !
#247
b11111111111111111111101000100000 #
b11111111111111111111111111111000 !
#248
b11111111111111111111101000100011 #
b11111111111111111111111111110111 !
#249
b11111111111111111111101000100010 #
b11111111111111111111111111110110 !
#250
b11111111111111111111101000100001 #
b11111111111111111111111111110101 !
#251
b11111111111111111111101000100000 #
b11111111111111111111111111110100 !
#252
b11111111111111111111101000100011 #
b11111111111111111111111111110011 !
#253
b11111111111111111111101000100010 #
b11111111111111111111111111110010 !
#254
b11111111111111111111101000100001 #
b11111111111111111111111111110001 !
#255
b11111111111111111111101000100000 #
b11111111111111111111111111110000 !
#256
b11111111111111111111101000100011 #
b11111111111111111111111111101111 !
#257
b11111111111111111111100110101111 #
b11111111111111111111100110111111 "
