add.v
module add(sum,carry_overflow,A,B,cin);
	input signed [63:0] A,B;
	input cin;
	output signed [63:0] sum;
	output signed carry_overflow;
	wire [18:0] carry;
	wire [2:0] t1,t2,t3;
	genvar i;
	CLA_FULL c1(sum[3:0],carry[0],A[3:0],B[3:0],cin);
	generate for(i=0;i<14;i=i+1)
		CLA_FULL c2(sum[7+4*i:4+4*i],carry[1+i],A[7+4*i:4+4*i],B[7+4*i:4+4*i],carry[0+i]);
	endgenerate
	CLA_FULL c16(sum[63:60],carry[18],A[63:60],B[63:60],carry[14]);
	generate for(i=0;i<3;i=i+1)
	begin
    		and gate2(t1[i],A[i+60],B[i+60]);
    		and gate3(t2[i],B[i+60],carry[i+14]);
    		and gate4(t3[i],A[i+60],carry[i+14]);
    		or gate5(carry[i+1+14],t1[i],t2[i],t3[i]);
	end
	endgenerate
       	xor(carry_overflow,carry[17],carry[18]);
endmodule 

module PG(p, g, a, b);
	input a, b;
	output p, g;
	and G1 (g, a, b);
	xor G2 (p, a, b);
endmodule

module CLA(g0, p0, g1, p1, g2, p2, g3, p3, c0, c1, c2, c3, c4);
	input g0, p0, g1, p1, g2, p2, g3, p3, c0;
	output c1, c2, c3, c4;
	wire t1, t2, t3, t4, t5, t6, t7, t8, t9, t10;
	and G1(t1, p0, c0);
	or G2(c1, t1, g0);
	
	and G3(t2, c0, p0, p1);
	and G4(t3, g0, p1);
	or G5(c2, g1, t2, t3);

	and G6(t4, c0, p0, p1, p2);
	and G7(t5, g0, p1, p2);
	and G8(t6, g1, p2);
	or G9(c3, g2, t4, t5, t6);
	
	and G10(t7, c0, p0, p1, p2, p3);
	and G11(t8, g0, p1, p2, p3);
	and G12(t9, g1, p2, p3);
	and G13(t10, g2, p3);
	or G14(c4, g3, t7, t8, t9, t10);
endmodule

module SUM(p0, c0, p1, c1, p2, c2, p3, c3, sum0, sum1, sum2, sum3);
	input p0, c0, p1, c1, p2, c2, p3, c3;
	output sum0, sum1, sum2, sum3;
	xor G1(sum0, p0, c0);
	xor G2(sum1, p1, c1);
	xor G3(sum2, p2, c2);
	xor G4(sum3, p3, c3);
endmodule

module CLA_FINAL(a3, b3, a2, b2, a1, b1, a0, b0, c0, c4, sum3, sum2, sum1, sum0);
	input a3, b3, a2, b2, a1, b1, a0, b0, c0;
	output c4, sum3, sum2, sum1, sum0;
	wire g0, p0, g1, p1, g2, p2, g3, p3, c1, c2, c3;
	PG B1(p0, g0, a0, b0);
	PG B2(p1, g1, a1, b1);
	PG B3(p2, g2, a2, b2);
	PG B4(p3, g3, a3, b3);
	CLA B5(g0, p0, g1, p1, g2, p2, g3, p3, c0, c1, c2, c3, c4);
	SUM B6(p0, c0, p1, c1, p2, c2, p3, c3, sum0, sum1, sum2, sum3);
endmodule

module CLA_FULL(sum,cout,a,b,cin);
	input [3:0] a,b;
	input cin;
	output [3:0] sum;
	output cout;
	CLA_FINAL F1(a[3], b[3], a[2], b[2], a[1], b[1], a[0], b[0], cin, cout, sum[3], sum[2], sum[1], sum[0]);
endmodule

add_tb.v
`include"add.v"
`timescale 1ps / 1ps 
module testbench;
	reg [63:0] a,b;
	reg cin;
	wire [63:0] out;
	wire c;
	integer i,k;
	add DUT(out,c,a,b,cin);
	initial begin
	//$monitor ($time,"ns: a = %b,\n\t\t        b = %b,\n\t\t       sum= %b, carry=%b \n",a, b, out,c); 
	$dumpfile("add.vcd");
    	$dumpvars(0,a,b,c,out);
	b=2**10-1;
	a=2**10-1;
	cin=0;
	#10;
	for(i=0; i<=2**4-1; i++) begin
		a=2**10-1;
		for(k=0;k<=2**4-1;k++) begin
		a--;
		#10;
		end
		b--;
	end
	end
endmodule

xor64.vcd
$date
	Wed Feb 02 21:19:37 2022
$end
$version
	Icarus Verilog
$end
$timescale
	10ns
$end
$scope module testbench $end
$var reg 64 ! a [63:0] $end
$upscope $end
$scope module testbench $end
$var reg 64 " b [63:0] $end
$upscope $end
$scope module testbench $end
$var wire 64 # out [63:0] $end
$upscope $end
$enddefinitions $end
#0
$dumpvars
b0 #
b11111111111111111111111111111111 "
b11111111111111111111111111111111 !
$end
#1
b1 #
b11111111111111111111111111111110 !
#2
b10 #
b11111111111111111111111111111101 !
#3
b11 #
b11111111111111111111111111111100 !
#4
b100 #
b11111111111111111111111111111011 !
#5
b101 #
b11111111111111111111111111111010 !
#6
b110 #
b11111111111111111111111111111001 !
#7
b111 #
b11111111111111111111111111111000 !
#8
b1000 #
b11111111111111111111111111110111 !
#9
b1001 #
b11111111111111111111111111110110 !
#10
b1010 #
b11111111111111111111111111110101 !
#11
b1011 #
b11111111111111111111111111110100 !
#12
b1100 #
b11111111111111111111111111110011 !
#13
b1101 #
b11111111111111111111111111110010 !
#14
b1110 #
b11111111111111111111111111110001 !
#15
b1111 #
b11111111111111111111111111110000 !
#16
b10000 #
b11111111111111111111111111101111 !
#17
b1100101 #
b11111111111111111111111111111110 !
b11111111111111111111111110011011 "
#18
b1100110 #
b11111111111111111111111111111101 !
#19
b1100111 #
b11111111111111111111111111111100 !
#20
b1100000 #
b11111111111111111111111111111011 !
#21
b1100001 #
b11111111111111111111111111111010 !
#22
b1100010 #
b11111111111111111111111111111001 !
#23
b1100011 #
b11111111111111111111111111111000 !
#24
b1101100 #
b11111111111111111111111111110111 !
#25
b1101101 #
b11111111111111111111111111110110 !
#26
b1101110 #
b11111111111111111111111111110101 !
#27
b1101111 #
b11111111111111111111111111110100 !
#28
b1101000 #
b11111111111111111111111111110011 !
#29
b1101001 #
b11111111111111111111111111110010 !
#30
b1101010 #
b11111111111111111111111111110001 !
#31
b1101011 #
b11111111111111111111111111110000 !
#32
b1110100 #
b11111111111111111111111111101111 !
#33
b11001001 #
b11111111111111111111111111111110 !
b11111111111111111111111100110111 "
#34
b11001010 #
b11111111111111111111111111111101 !
#35
b11001011 #
b11111111111111111111111111111100 !
#36
b11001100 #
b11111111111111111111111111111011 !
#37
b11001101 #
b11111111111111111111111111111010 !
#38
b11001110 #
b11111111111111111111111111111001 !
#39
b11001111 #
b11111111111111111111111111111000 !
#40
b11000000 #
b11111111111111111111111111110111 !
#41
b11000001 #
b11111111111111111111111111110110 !
#42
b11000010 #
b11111111111111111111111111110101 !
#43
b11000011 #
b11111111111111111111111111110100 !
#44
b11000100 #
b11111111111111111111111111110011 !
#45
b11000101 #
b11111111111111111111111111110010 !
#46
b11000110 #
b11111111111111111111111111110001 !
#47
b11000111 #
b11111111111111111111111111110000 !
#48
b11011000 #
b11111111111111111111111111101111 !
#49
b100101101 #
b11111111111111111111111111111110 !
b11111111111111111111111011010011 "
#50
b100101110 #
b11111111111111111111111111111101 !
#51
b100101111 #
b11111111111111111111111111111100 !
#52
b100101000 #
b11111111111111111111111111111011 !
#53
b100101001 #
b11111111111111111111111111111010 !
#54
b100101010 #
b11111111111111111111111111111001 !
#55
b100101011 #
b11111111111111111111111111111000 !
#56
b100100100 #
b11111111111111111111111111110111 !
#57
b100100101 #
b11111111111111111111111111110110 !
#58
b100100110 #
b11111111111111111111111111110101 !
#59
b100100111 #
b11111111111111111111111111110100 !
#60
b100100000 #
b11111111111111111111111111110011 !
#61
b100100001 #
b11111111111111111111111111110010 !
#62
b100100010 #
b11111111111111111111111111110001 !
#63
b100100011 #
b11111111111111111111111111110000 !
#64
b100111100 #
b11111111111111111111111111101111 !
#65
b110010001 #
b11111111111111111111111111111110 !
b11111111111111111111111001101111 "
#66
b110010010 #
b11111111111111111111111111111101 !
#67
b110010011 #
b11111111111111111111111111111100 !
#68
b110010100 #
b11111111111111111111111111111011 !
#69
b110010101 #
b11111111111111111111111111111010 !
#70
b110010110 #
b11111111111111111111111111111001 !
#71
b110010111 #
b11111111111111111111111111111000 !
#72
b110011000 #
b11111111111111111111111111110111 !
#73
b110011001 #
b11111111111111111111111111110110 !
#74
b110011010 #
b11111111111111111111111111110101 !
#75
b110011011 #
b11111111111111111111111111110100 !
#76
b110011100 #
b11111111111111111111111111110011 !
#77
b110011101 #
b11111111111111111111111111110010 !
#78
b110011110 #
b11111111111111111111111111110001 !
#79
b110011111 #
b11111111111111111111111111110000 !
#80
b110000000 #
b11111111111111111111111111101111 !
#81
b111110101 #
b11111111111111111111111111111110 !
b11111111111111111111111000001011 "
#82
b111110110 #
b11111111111111111111111111111101 !
#83
b111110111 #
b11111111111111111111111111111100 !
#84
b111110000 #
b11111111111111111111111111111011 !
#85
b111110001 #
b11111111111111111111111111111010 !
#86
b111110010 #
b11111111111111111111111111111001 !
#87
b111110011 #
b11111111111111111111111111111000 !
#88
b111111100 #
b11111111111111111111111111110111 !
#89
b111111101 #
b11111111111111111111111111110110 !
#90
b111111110 #
b11111111111111111111111111110101 !
#91
b111111111 #
b11111111111111111111111111110100 !
#92
b111111000 #
b11111111111111111111111111110011 !
#93
b111111001 #
b11111111111111111111111111110010 !
#94
b111111010 #
b11111111111111111111111111110001 !
#95
b111111011 #
b11111111111111111111111111110000 !
#96
b111100100 #
b11111111111111111111111111101111 !
#97
b1001011001 #
b11111111111111111111111111111110 !
b11111111111111111111110110100111 "
#98
b1001011010 #
b11111111111111111111111111111101 !
#99
b1001011011 #
b11111111111111111111111111111100 !
#100
b1001011100 #
b11111111111111111111111111111011 !
#101
b1001011101 #
b11111111111111111111111111111010 !
#102
b1001011110 #
b11111111111111111111111111111001 !
#103
b1001011111 #
b11111111111111111111111111111000 !
#104
b1001010000 #
b11111111111111111111111111110111 !
#105
b1001010001 #
b11111111111111111111111111110110 !
#106
b1001010010 #
b11111111111111111111111111110101 !
#107
b1001010011 #
b11111111111111111111111111110100 !
#108
b1001010100 #
b11111111111111111111111111110011 !
#109
b1001010101 #
b11111111111111111111111111110010 !
#110
b1001010110 #
b11111111111111111111111111110001 !
#111
b1001010111 #
b11111111111111111111111111110000 !
#112
b1001001000 #
b11111111111111111111111111101111 !
#113
b1010111101 #
b11111111111111111111111111111110 !
b11111111111111111111110101000011 "
#114
b1010111110 #
b11111111111111111111111111111101 !
#115
b1010111111 #
b11111111111111111111111111111100 !
#116
b1010111000 #
b11111111111111111111111111111011 !
#117
b1010111001 #
b11111111111111111111111111111010 !
#118
b1010111010 #
b11111111111111111111111111111001 !
#119
b1010111011 #
b11111111111111111111111111111000 !
#120
b1010110100 #
b11111111111111111111111111110111 !
#121
b1010110101 #
b11111111111111111111111111110110 !
#122
b1010110110 #
b11111111111111111111111111110101 !
#123
b1010110111 #
b11111111111111111111111111110100 !
#124
b1010110000 #
b11111111111111111111111111110011 !
#125
b1010110001 #
b11111111111111111111111111110010 !
#126
b1010110010 #
b11111111111111111111111111110001 !
#127
b1010110011 #
b11111111111111111111111111110000 !
#128
b1010101100 #
b11111111111111111111111111101111 !
#129
b1100100001 #
b11111111111111111111111111111110 !
b11111111111111111111110011011111 "
#130
b1100100010 #
b11111111111111111111111111111101 !
#131
b1100100011 #
b11111111111111111111111111111100 !
#132
b1100100100 #
b11111111111111111111111111111011 !
#133
b1100100101 #
b11111111111111111111111111111010 !
#134
b1100100110 #
b11111111111111111111111111111001 !
#135
b1100100111 #
b11111111111111111111111111111000 !
#136
b1100101000 #
b11111111111111111111111111110111 !
#137
b1100101001 #
b11111111111111111111111111110110 !
#138
b1100101010 #
b11111111111111111111111111110101 !
#139
b1100101011 #
b11111111111111111111111111110100 !
#140
b1100101100 #
b11111111111111111111111111110011 !
#141
b1100101101 #
b11111111111111111111111111110010 !
#142
b1100101110 #
b11111111111111111111111111110001 !
#143
b1100101111 #
b11111111111111111111111111110000 !
#144
b1100110000 #
b11111111111111111111111111101111 !
#145
b1110000101 #
b11111111111111111111111111111110 !
b11111111111111111111110001111011 "
#146
b1110000110 #
b11111111111111111111111111111101 !
#147
b1110000111 #
b11111111111111111111111111111100 !
#148
b1110000000 #
b11111111111111111111111111111011 !
#149
b1110000001 #
b11111111111111111111111111111010 !
#150
b1110000010 #
b11111111111111111111111111111001 !
#151
b1110000011 #
b11111111111111111111111111111000 !
#152
b1110001100 #
b11111111111111111111111111110111 !
#153
b1110001101 #
b11111111111111111111111111110110 !
#154
b1110001110 #
b11111111111111111111111111110101 !
#155
b1110001111 #
b11111111111111111111111111110100 !
#156
b1110001000 #
b11111111111111111111111111110011 !
#157
b1110001001 #
b11111111111111111111111111110010 !
#158
b1110001010 #
b11111111111111111111111111110001 !
#159
b1110001011 #
b11111111111111111111111111110000 !
#160
b1110010100 #
b11111111111111111111111111101111 !
#161
b1111101001 #
b11111111111111111111111111111110 !
b11111111111111111111110000010111 "
#162
b1111101010 #
b11111111111111111111111111111101 !
#163
b1111101011 #
b11111111111111111111111111111100 !
#164
b1111101100 #
b11111111111111111111111111111011 !
#165
b1111101101 #
b11111111111111111111111111111010 !
#166
b1111101110 #
b11111111111111111111111111111001 !
#167
b1111101111 #
b11111111111111111111111111111000 !
#168
b1111100000 #
b11111111111111111111111111110111 !
#169
b1111100001 #
b11111111111111111111111111110110 !
#170
b1111100010 #
b11111111111111111111111111110101 !
#171
b1111100011 #
b11111111111111111111111111110100 !
#172
b1111100100 #
b11111111111111111111111111110011 !
#173
b1111100101 #
b11111111111111111111111111110010 !
#174
b1111100110 #
b11111111111111111111111111110001 !
#175
b1111100111 #
b11111111111111111111111111110000 !
#176
b1111111000 #
b11111111111111111111111111101111 !
#177
b10001001101 #
b11111111111111111111111111111110 !
b11111111111111111111101110110011 "
#178
b10001001110 #
b11111111111111111111111111111101 !
#179
b10001001111 #
b11111111111111111111111111111100 !
#180
b10001001000 #
b11111111111111111111111111111011 !
#181
b10001001001 #
b11111111111111111111111111111010 !
#182
b10001001010 #
b11111111111111111111111111111001 !
#183
b10001001011 #
b11111111111111111111111111111000 !
#184
b10001000100 #
b11111111111111111111111111110111 !
#185
b10001000101 #
b11111111111111111111111111110110 !
#186
b10001000110 #
b11111111111111111111111111110101 !
#187
b10001000111 #
b11111111111111111111111111110100 !
#188
b10001000000 #
b11111111111111111111111111110011 !
#189
b10001000001 #
b11111111111111111111111111110010 !
#190
b10001000010 #
b11111111111111111111111111110001 !
#191
b10001000011 #
b11111111111111111111111111110000 !
#192
b10001011100 #
b11111111111111111111111111101111 !
#193
b10010110001 #
b11111111111111111111111111111110 !
b11111111111111111111101101001111 "
#194
b10010110010 #
b11111111111111111111111111111101 !
#195
b10010110011 #
b11111111111111111111111111111100 !
#196
b10010110100 #
b11111111111111111111111111111011 !
#197
b10010110101 #
b11111111111111111111111111111010 !
#198
b10010110110 #
b11111111111111111111111111111001 !
#199
b10010110111 #
b11111111111111111111111111111000 !
#200
b10010111000 #
b11111111111111111111111111110111 !
#201
b10010111001 #
b11111111111111111111111111110110 !
#202
b10010111010 #
b11111111111111111111111111110101 !
#203
b10010111011 #
b11111111111111111111111111110100 !
#204
b10010111100 #
b11111111111111111111111111110011 !
#205
b10010111101 #
b11111111111111111111111111110010 !
#206
b10010111110 #
b11111111111111111111111111110001 !
#207
b10010111111 #
b11111111111111111111111111110000 !
#208
b10010100000 #
b11111111111111111111111111101111 !
#209
b10100010101 #
b11111111111111111111111111111110 !
b11111111111111111111101011101011 "
#210
b10100010110 #
b11111111111111111111111111111101 !
#211
b10100010111 #
b11111111111111111111111111111100 !
#212
b10100010000 #
b11111111111111111111111111111011 !
#213
b10100010001 #
b11111111111111111111111111111010 !
#214
b10100010010 #
b11111111111111111111111111111001 !
#215
b10100010011 #
b11111111111111111111111111111000 !
#216
b10100011100 #
b11111111111111111111111111110111 !
#217
b10100011101 #
b11111111111111111111111111110110 !
#218
b10100011110 #
b11111111111111111111111111110101 !
#219
b10100011111 #
b11111111111111111111111111110100 !
#220
b10100011000 #
b11111111111111111111111111110011 !
#221
b10100011001 #
b11111111111111111111111111110010 !
#222
b10100011010 #
b11111111111111111111111111110001 !
#223
b10100011011 #
b11111111111111111111111111110000 !
#224
b10100000100 #
b11111111111111111111111111101111 !
#225
b10101111001 #
b11111111111111111111111111111110 !
b11111111111111111111101010000111 "
#226
b10101111010 #
b11111111111111111111111111111101 !
#227
b10101111011 #
b11111111111111111111111111111100 !
#228
b10101111100 #
b11111111111111111111111111111011 !
#229
b10101111101 #
b11111111111111111111111111111010 !
#230
b10101111110 #
b11111111111111111111111111111001 !
#231
b10101111111 #
b11111111111111111111111111111000 !
#232
b10101110000 #
b11111111111111111111111111110111 !
#233
b10101110001 #
b11111111111111111111111111110110 !
#234
b10101110010 #
b11111111111111111111111111110101 !
#235
b10101110011 #
b11111111111111111111111111110100 !
#236
b10101110100 #
b11111111111111111111111111110011 !
#237
b10101110101 #
b11111111111111111111111111110010 !
#238
b10101110110 #
b11111111111111111111111111110001 !
#239
b10101110111 #
b11111111111111111111111111110000 !
#240
b10101101000 #
b11111111111111111111111111101111 !
#241
b10111011101 #
b11111111111111111111111111111110 !
b11111111111111111111101000100011 "
#242
b10111011110 #
b11111111111111111111111111111101 !
#243
b10111011111 #
b11111111111111111111111111111100 !
#244
b10111011000 #
b11111111111111111111111111111011 !
#245
b10111011001 #
b11111111111111111111111111111010 !
#246
b10111011010 #
b11111111111111111111111111111001 !
#247
b10111011011 #
b11111111111111111111111111111000 !
#248
b10111010100 #
b11111111111111111111111111110111 !
#249
b10111010101 #
b11111111111111111111111111110110 !
#250
b10111010110 #
b11111111111111111111111111110101 !
#251
b10111010111 #
b11111111111111111111111111110100 !
#252
b10111010000 #
b11111111111111111111111111110011 !
#253
b10111010001 #
b11111111111111111111111111110010 !
#254
b10111010010 #
b11111111111111111111111111110001 !
#255
b10111010011 #
b11111111111111111111111111110000 !
#256
b10111001100 #
b11111111111111111111111111101111 !
#257
b11001010000 #
b11111111111111111111100110111111 "
